slack_alert.py
slack_alert-0.1.5.dist-info/DESCRIPTION.rst
slack_alert-0.1.5.dist-info/entry_points.txt
slack_alert-0.1.5.dist-info/METADATA
slack_alert-0.1.5.dist-info/metadata.json
slack_alert-0.1.5.dist-info/RECORD
slack_alert-0.1.5.dist-info/top_level.txt
slack_alert-0.1.5.dist-info/WHEEL
