Metadata-Version: 2.0
Name: slack-alert
Version: 0.1.5
Summary: Send message onto a channel when this need be alerted under Python3
Home-page: https://github.com/dongweiming/slack-alert
Author: DongWeiming
Author-email: ciici123@gmail.com
License: MIT
Keywords: slack
Platform: UNKNOWN
Classifier: Intended Audience :: Developers
Classifier: Natural Language :: English
Classifier: Programming Language :: Python :: 3
Classifier: Programming Language :: Python :: 3.3
Classifier: Programming Language :: Python :: 3.4
Requires-Dist: slacker
Requires-Dist: apscheduler
Requires-Dist: tornado
Requires-Dist: gevent (==1.1b1)
